edea_tmc/__init__.py
edea_tmc/local.py
edea_tmc/remote.py
edea_tmc/runner.py
edea_tmc/sequencer.py
edea_tmc/stepper.py
edea_tmc-0.2.3.dist-info/METADATA
edea_tmc-0.2.3.dist-info/WHEEL
edea_tmc-0.2.3.dist-info/RECORD
