Metadata-Version: 2.3
Name: edea-tmc
Version: 0.2.3
Summary: Test and Measurement as Code library for EDeA-MS
Author-email: Elen Eisendle <ln@calcifer.ee>
Requires-Python: <3.13,>=3.11
Provides-Extra: interactive
Requires-Dist: tqdm>=4.66.6; extra == 'interactive'
Provides-Extra: jupyter
Requires-Dist: ipywidgets>=8.1.5; extra == 'jupyter'
Requires-Dist: jupyter>=1.1.1; extra == 'jupyter'
Provides-Extra: pandas
Requires-Dist: pandas>=2.2.3; extra == 'pandas'
Provides-Extra: polars
Requires-Dist: polars>=1.12.0; extra == 'polars'
Provides-Extra: remote
Requires-Dist: httpx>=0.27.2; extra == 'remote'
